{
    "prepare_queue": {
        "installed": [],
        "uninstalled": []
    },
    "config_munge": {
        "files": {}
    },
    "installed_plugins": {
        "cordova-plugin-whitelist": {
            "PACKAGE_NAME": "com.KenyaKobayashi.fileupload"
        },
        "cordova-plugin-device": {
            "PACKAGE_NAME": "com.KenyaKobayashi.fileupload"
        },
        "cordova-plugin-console": {
            "PACKAGE_NAME": "com.KenyaKobayashi.fileupload"
        }
    },
    "dependent_plugins": {}
}